{"title":"simply_amazing.mobile.mp4","uid":12399760,"size":228917551,"categoryP":"porn","categoryS":"movie_clips","magnet":"?xt=urn:btih:00fe85a318b39fcd15c59cb1ceb103eb00ead125&amp;dn=simply_amazing.mobile.mp4&amp;tr=udp%3A%2F%2Ftracker.openbittorrent.com%3A80&amp;tr=udp%3A%2F%2Fopen.demonii.com%3A1337&amp;tr=udp%3A%2F%2Ftracker.coppersurfer.tk%3A6969&amp;tr=udp%3A%2F%2Fexodus.desync.com%3A6969","seeders":1,"leechers":0,"uploader":"Piratepr0n","files":1,"time":1442005946,"description":"-------------------------------------------------------------------------------------\nName:\nsimply_amazing.mobile.mp4\n-------------------------------------------------------------------------------------\nFile list:\nsimply_amazing.mobile.mp4 (218 MiB | 480x270 | 36min 12s | MPEG-4) &lt;a href=&quot;\nhttp://imgfapper.com/img-55f3287da2424.html&quot; rel=&quot;nofollow&quot; target=&quot;_NEW&quot;&gt;\nhttp://imgfapper.com/img-55f3287da2424.html&lt;/a&gt;","torrent":{"xt":"urn:btih:00fe85a318b39fcd15c59cb1ceb103eb00ead125","amp;dn":"simply_amazing.mobile.mp4","amp;tr":["udp%3A%2F%2Ftracker.openbittorrent.com%3A80","udp%3A%2F%2Fopen.demonii.com%3A1337","udp%3A%2F%2Ftracker.coppersurfer.tk%3A6969","udp%3A%2F%2Fexodus.desync.com%3A6969"],"infoHash":"00fe85a318b39fcd15c59cb1ceb103eb00ead125","infoHashBuffer":{"type":"Buffer","data":[0,254,133,163,24,179,159,205,21,197,156,177,206,177,3,235,0,234,209,37]},"announce":[],"urlList":[]}}