{"title":"Supersize.Me.Monster.Cocks.XXX.DVDRip.x264-Jiggly","uid":8228493,"size":1113679419,"categoryP":"porn","categoryS":"movies","magnet":"?xt=urn:btih:15354a6cf6e7a16d615ba7606275955beb3b8de3&amp;dn=Supersize.Me.Monster.Cocks.XXX.DVDRip.x264-Jiggly&amp;tr=udp%3A%2F%2Ftracker.openbittorrent.com%3A80&amp;tr=udp%3A%2F%2Fopen.demonii.com%3A1337&amp;tr=udp%3A%2F%2Ftracker.coppersurfer.tk%3A6969&amp;tr=udp%3A%2F%2Fexodus.desync.com%3A6969","seeders":1,"leechers":0,"uploader":"R0thschild","files":2,"time":1362671862,"description":"Gallery: \n &lt;a href=&quot;\nhttp://hqpdb.com/viewtopic.php?f=9&amp;t=37298&quot; rel=&quot;nofollow&quot; target=&quot;_NEW&quot;&gt;\nhttp://hqpdb.com/viewtopic.php?f=9&amp;t=37298&lt;/a&gt;\n\n------------------------------------------\n         My torrents at thePiratebay\n------------------------------------------\n   &lt;a href=&quot;\nhttp://thepiratebay.se/user/R0thschild/&quot; rel=&quot;nofollow&quot; target=&quot;_NEW&quot;&gt;\nhttp://thepiratebay.se/user/R0thschild/&lt;/a&gt;\t","torrent":{"xt":"urn:btih:15354a6cf6e7a16d615ba7606275955beb3b8de3","amp;dn":"Supersize.Me.Monster.Cocks.XXX.DVDRip.x264-Jiggly","amp;tr":["udp%3A%2F%2Ftracker.openbittorrent.com%3A80","udp%3A%2F%2Fopen.demonii.com%3A1337","udp%3A%2F%2Ftracker.coppersurfer.tk%3A6969","udp%3A%2F%2Fexodus.desync.com%3A6969"],"infoHash":"15354a6cf6e7a16d615ba7606275955beb3b8de3","infoHashBuffer":{"type":"Buffer","data":[21,53,74,108,246,231,161,109,97,91,167,96,98,117,149,91,235,59,141,227]},"announce":[],"urlList":[]}}