{"title":"My Ass Is Hungry (2012) SiteRip","uid":8150931,"size":310488159,"categoryP":"porn","categoryS":"movie_clips","magnet":"?xt=urn:btih:1dbadbcb605117191778138f8db2f6a032d26edf&amp;dn=My+Ass+Is+Hungry+%282012%29+SiteRip&amp;tr=udp%3A%2F%2Ftracker.openbittorrent.com%3A80&amp;tr=udp%3A%2F%2Fopen.demonii.com%3A1337&amp;tr=udp%3A%2F%2Ftracker.coppersurfer.tk%3A6969&amp;tr=udp%3A%2F%2Fexodus.desync.com%3A6969","seeders":1,"leechers":0,"uploader":"Programsmith","files":-1,"time":1361033287,"description":"Title: My Ass Is Hungry\nGenre: Anal, Natural Tits, Deep Throat, Exhibitionist, Teen, Big Ass, Hardcore\nStarring: Cristal Cherry\n\nDescription: I wanted to get in the ass - got ..\n\nDuration: 00:40:37\nLanguage: English\n\nfile\nQuality: SiteRip\nFormat: MP4\nVideo: MPEG4 Video (H264) 480x272 25.00fps 888kbps\nAudio: AAC 48000Hz stereo 128kb\n\n &lt;a href=&quot;\nhttp://imgload.me/img-511fa8a4f3d35.html&quot; rel=&quot;nofollow&quot; target=&quot;_NEW&quot;&gt;\nhttp://imgload.me/img-511fa8a4f3d35.html&lt;/a&gt; ","torrent":{"xt":"urn:btih:1dbadbcb605117191778138f8db2f6a032d26edf","amp;dn":"My+Ass+Is+Hungry+%282012%29+SiteRip","amp;tr":["udp%3A%2F%2Ftracker.openbittorrent.com%3A80","udp%3A%2F%2Fopen.demonii.com%3A1337","udp%3A%2F%2Ftracker.coppersurfer.tk%3A6969","udp%3A%2F%2Fexodus.desync.com%3A6969"],"infoHash":"1dbadbcb605117191778138f8db2f6a032d26edf","infoHashBuffer":{"type":"Buffer","data":[29,186,219,203,96,81,23,25,23,120,19,143,141,178,246,160,50,210,110,223]},"announce":[],"urlList":[]}}