{"title":"Americas.Next.Top.Model.S21E02.HDTV.XviD-AFG","uid":10883471,"size":885811329,"categoryP":"video","categoryS":"tv_shows","magnet":"?xt=urn:btih:27b327f7947734f97963d5d5d59b622cca60b0cb&amp;dn=Americas.Next.Top.Model.S21E02.HDTV.XviD-AFG&amp;tr=udp%3A%2F%2Ftracker.openbittorrent.com%3A80&amp;tr=udp%3A%2F%2Fopen.demonii.com%3A1337&amp;tr=udp%3A%2F%2Ftracker.coppersurfer.tk%3A6969&amp;tr=udp%3A%2F%2Fexodus.desync.com%3A6969","seeders":1,"leechers":0,"uploader":"TvTeam","files":4,"time":1409058456,"description":" &lt;a href=&quot;http://www.torrenting.com&quot; rel=&quot;nofollow&quot; target=&quot;_NEW&quot;&gt;http://www.torrenting.com&lt;/a&gt;\n\nSign up is OPEN - for time being. Come and have fun.","torrent":{"xt":"urn:btih:27b327f7947734f97963d5d5d59b622cca60b0cb","amp;dn":"Americas.Next.Top.Model.S21E02.HDTV.XviD-AFG","amp;tr":["udp%3A%2F%2Ftracker.openbittorrent.com%3A80","udp%3A%2F%2Fopen.demonii.com%3A1337","udp%3A%2F%2Ftracker.coppersurfer.tk%3A6969","udp%3A%2F%2Fexodus.desync.com%3A6969"],"infoHash":"27b327f7947734f97963d5d5d59b622cca60b0cb","infoHashBuffer":{"type":"Buffer","data":[39,179,39,247,148,119,52,249,121,99,213,213,213,155,98,44,202,96,176,203]},"announce":[],"urlList":[]}}