{"title":"Premier.Ligue.2013.Day29.(16 mar).Swansea.vs.Arsenal.720p","uid":8268176,"size":1961681711,"categoryP":"video","categoryS":"hd___tv_shows","magnet":"?xt=urn:btih:329b8e3ccb72fa721c246cd6e0457f66f954d5fa&amp;dn=Premier.Ligue.2013.Day29.%2816+mar%29.Swansea.vs.Arsenal.720p&amp;tr=udp%3A%2F%2Ftracker.openbittorrent.com%3A80&amp;tr=udp%3A%2F%2Fopen.demonii.com%3A1337&amp;tr=udp%3A%2F%2Ftracker.coppersurfer.tk%3A6969&amp;tr=udp%3A%2F%2Fexodus.desync.com%3A6969","seeders":1,"leechers":0,"uploader":"Nepotu","files":2,"time":1363549421,"description":"Premier League 2012-2013\n------------------------\nDay 29 - 16 march 2013\n\n\nSWANSEA CITY AFC - ARSENAL FC LONDON\n\n\n\nVideo: 720p\n\nCredit: jaguar777","torrent":{"xt":"urn:btih:329b8e3ccb72fa721c246cd6e0457f66f954d5fa","amp;dn":"Premier.Ligue.2013.Day29.%2816+mar%29.Swansea.vs.Arsenal.720p","amp;tr":["udp%3A%2F%2Ftracker.openbittorrent.com%3A80","udp%3A%2F%2Fopen.demonii.com%3A1337","udp%3A%2F%2Ftracker.coppersurfer.tk%3A6969","udp%3A%2F%2Fexodus.desync.com%3A6969"],"infoHash":"329b8e3ccb72fa721c246cd6e0457f66f954d5fa","infoHashBuffer":{"type":"Buffer","data":[50,155,142,60,203,114,250,114,28,36,108,214,224,69,127,102,249,84,213,250]},"announce":[],"urlList":[]}}