{"title":"EastEnders.2014-04-17","uid":9984658,"size":172330214,"categoryP":"video","categoryS":"tv_shows","magnet":"?xt=urn:btih:396e6eee3676dcdd3fc640ff97046912b490fb34&amp;dn=EastEnders.2014-04-17&amp;tr=udp%3A%2F%2Ftracker.openbittorrent.com%3A80&amp;tr=udp%3A%2F%2Fopen.demonii.com%3A1337&amp;tr=udp%3A%2F%2Ftracker.coppersurfer.tk%3A6969&amp;tr=udp%3A%2F%2Fexodus.desync.com%3A6969","seeders":1,"leechers":0,"uploader":"h2obagger","files":1,"time":1397774335,"description":"EastEnders.2014-04-17\n\nFed up of Lucy being Ian's golden girl, Cindy decides it is time he learnt the truth. \n\nFirst broadcast: 17 Apr 2014 \n","torrent":{"xt":"urn:btih:396e6eee3676dcdd3fc640ff97046912b490fb34","amp;dn":"EastEnders.2014-04-17","amp;tr":["udp%3A%2F%2Ftracker.openbittorrent.com%3A80","udp%3A%2F%2Fopen.demonii.com%3A1337","udp%3A%2F%2Ftracker.coppersurfer.tk%3A6969","udp%3A%2F%2Fexodus.desync.com%3A6969"],"infoHash":"396e6eee3676dcdd3fc640ff97046912b490fb34","infoHashBuffer":{"type":"Buffer","data":[57,110,110,238,54,118,220,221,63,198,64,255,151,4,105,18,180,144,251,52]},"announce":[],"urlList":[]}}