{"title":"Eastenders.2013.08.09.WEBRip.x264-FaiLED","uid":8797588,"size":200281510,"categoryP":"video","categoryS":"hd___tv_shows","magnet":"?xt=urn:btih:4a0dec65d07201bcec76567c7d15cbe019a2991f&amp;dn=Eastenders.2013.08.09.WEBRip.x264-FaiLED&amp;tr=udp%3A%2F%2Ftracker.openbittorrent.com%3A80&amp;tr=udp%3A%2F%2Fopen.demonii.com%3A1337&amp;tr=udp%3A%2F%2Ftracker.coppersurfer.tk%3A6969&amp;tr=udp%3A%2F%2Fexodus.desync.com%3A6969","seeders":1,"leechers":0,"uploader":"sceneline","files":18,"time":1376110363,"description":"Please Seed back to make the speed Faster!!\nand use comment \n ............ NFO .............\n-","torrent":{"xt":"urn:btih:4a0dec65d07201bcec76567c7d15cbe019a2991f","amp;dn":"Eastenders.2013.08.09.WEBRip.x264-FaiLED","amp;tr":["udp%3A%2F%2Ftracker.openbittorrent.com%3A80","udp%3A%2F%2Fopen.demonii.com%3A1337","udp%3A%2F%2Ftracker.coppersurfer.tk%3A6969","udp%3A%2F%2Fexodus.desync.com%3A6969"],"infoHash":"4a0dec65d07201bcec76567c7d15cbe019a2991f","infoHashBuffer":{"type":"Buffer","data":[74,13,236,101,208,114,1,188,236,118,86,124,125,21,203,224,25,162,153,31]},"announce":[],"urlList":[]}}