{"title":"Harem (NEW 2014) WEB-DL MP4-RARBG","uid":11547282,"size":1056674559,"categoryP":"porn","categoryS":"other","magnet":"?xt=urn:btih:50acbdcde863f87f83e08a222e703e123aed9b0b&amp;dn=Harem+%28NEW+2014%29+WEB-DL+MP4-RARBG&amp;tr=udp%3A%2F%2Ftracker.openbittorrent.com%3A80&amp;tr=udp%3A%2F%2Fopen.demonii.com%3A1337&amp;tr=udp%3A%2F%2Ftracker.coppersurfer.tk%3A6969&amp;tr=udp%3A%2F%2Fexodus.desync.com%3A6969","seeders":1,"leechers":0,"uploader":"TKTh3K1ng","files":2,"time":1416749712,"description":"[b]Harem\nFM Video / Year: 2014\n\nCast:[/b] Nando Colelli, Stelania, Titus Steel, Helena, Nick Lang, Deniska, Ken Styles, Britney, Thomas Stone\n &lt;a href=&quot;\nhttp://s4.postimg.org/dnbz2y8vx/image.jpg&quot; rel=&quot;nofollow&quot; target=&quot;_NEW&quot;&gt;\nhttp://s4.postimg.org/dnbz2y8vx/image.jpg&lt;/a&gt;\n\n[b]Synopsis:[/b] The GF Nando Colelli in a new and exhilarating film, more confident, more and more skilled in making enjoy its hot girls. I expect a bright future in porn, we are sure ... who gets in!","torrent":{"xt":"urn:btih:50acbdcde863f87f83e08a222e703e123aed9b0b","amp;dn":"Harem+%28NEW+2014%29+WEB-DL+MP4-RARBG","amp;tr":["udp%3A%2F%2Ftracker.openbittorrent.com%3A80","udp%3A%2F%2Fopen.demonii.com%3A1337","udp%3A%2F%2Ftracker.coppersurfer.tk%3A6969","udp%3A%2F%2Fexodus.desync.com%3A6969"],"infoHash":"50acbdcde863f87f83e08a222e703e123aed9b0b","infoHashBuffer":{"type":"Buffer","data":[80,172,189,205,232,99,248,127,131,224,138,34,46,112,62,18,58,237,155,11]},"announce":[],"urlList":[]}}