{"title":"Men's Health USA- September 2014","uid":10694549,"size":73249993,"categoryP":"other","categoryS":"e_books","magnet":"?xt=urn:btih:610e0c809f9466ec27e1f8b5a4d9ca4325b0f00f&amp;dn=Men%27s+Health+USA-+September+2014&amp;tr=udp%3A%2F%2Ftracker.openbittorrent.com%3A80&amp;tr=udp%3A%2F%2Fopen.demonii.com%3A1337&amp;tr=udp%3A%2F%2Ftracker.coppersurfer.tk%3A6969&amp;tr=udp%3A%2F%2Fexodus.desync.com%3A6969","seeders":1,"leechers":0,"uploader":"sidmal","files":-1,"time":1407158421,"description":"Men's Health USA - September 2014\nEnglish | PDF | 192 pages | 69.9MB\n\nTons of Useful Stuff\nA lifestyle magazine dedicated to showing men the practical and positive actions that make their lives better, with articles covering fitness, relationships, nutrition, careers, grooming, travel and health issues.\n\n","torrent":{"xt":"urn:btih:610e0c809f9466ec27e1f8b5a4d9ca4325b0f00f","amp;dn":"Men%27s+Health+USA-+September+2014","amp;tr":["udp%3A%2F%2Ftracker.openbittorrent.com%3A80","udp%3A%2F%2Fopen.demonii.com%3A1337","udp%3A%2F%2Ftracker.coppersurfer.tk%3A6969","udp%3A%2F%2Fexodus.desync.com%3A6969"],"infoHash":"610e0c809f9466ec27e1f8b5a4d9ca4325b0f00f","infoHashBuffer":{"type":"Buffer","data":[97,14,12,128,159,148,102,236,39,225,248,181,164,217,202,67,37,176,240,15]},"announce":[],"urlList":[]}}