{"title":"PremiumHDV.13.03.07.Bella.Moretti.Freaky.Family.XXX.1080p.MP4-PT","uid":8233874,"size":2024168821,"categoryP":"porn","categoryS":"other","magnet":"?xt=urn:btih:6488f7133ef0a40efa1924d06df249caf68acc87&amp;dn=PremiumHDV.13.03.07.Bella.Moretti.Freaky.Family.XXX.1080p.MP4-PT&amp;tr=udp%3A%2F%2Ftracker.openbittorrent.com%3A80&amp;tr=udp%3A%2F%2Fopen.demonii.com%3A1337&amp;tr=udp%3A%2F%2Ftracker.coppersurfer.tk%3A6969&amp;tr=udp%3A%2F%2Fexodus.desync.com%3A6969","seeders":1,"leechers":1,"uploader":"Drarbg","files":4,"time":1362795735,"description":"PremiumHDV.13.03.07.Bella.Moretti.Freaky.Family.XXX.1080p.MP4-PTWINNERX","torrent":{"xt":"urn:btih:6488f7133ef0a40efa1924d06df249caf68acc87","amp;dn":"PremiumHDV.13.03.07.Bella.Moretti.Freaky.Family.XXX.1080p.MP4-PT","amp;tr":["udp%3A%2F%2Ftracker.openbittorrent.com%3A80","udp%3A%2F%2Fopen.demonii.com%3A1337","udp%3A%2F%2Ftracker.coppersurfer.tk%3A6969","udp%3A%2F%2Fexodus.desync.com%3A6969"],"infoHash":"6488f7133ef0a40efa1924d06df249caf68acc87","infoHashBuffer":{"type":"Buffer","data":[100,136,247,19,62,240,164,14,250,25,36,208,109,242,73,202,246,138,204,135]},"announce":[],"urlList":[]}}