{"title":"Pain and Gain (2013) TELESYNC - 500MB - ShAaNiG","uid":8533649,"size":525571517,"categoryP":"video","categoryS":"movies","magnet":"?xt=urn:btih:6744dbde127490fe022a9b4b9660402a40e8104f&amp;dn=Pain+and+Gain+%282013%29+TELESYNC+-+500MB+-+ShAaNiG&amp;tr=udp%3A%2F%2Ftracker.openbittorrent.com%3A80&amp;tr=udp%3A%2F%2Fopen.demonii.com%3A1337&amp;tr=udp%3A%2F%2Ftracker.coppersurfer.tk%3A6969&amp;tr=udp%3A%2F%2Fexodus.desync.com%3A6969","seeders":1,"leechers":0,"uploader":"ShAaNiG","files":-1,"time":1370216529,"description":"ShAaNiG - High quality movies at smallest size\n\n      \n          &lt;a href=&quot; http://www.shaanig.com/&quot; rel=&quot;nofollow&quot; target=&quot;_NEW&quot;&gt; http://www.shaanig.com/&lt;/a&gt;\n    \n\n\n\n----------------------------------------------\n\n\n\nSTORYLiNE:\nBased on the true story of Daniel Lugo (Mark Wahlberg) a Miami bodybuilder who wants to live the American dream. He would like to have the money that other people have. So he enlists the help of fellow bodybuilder Adrian Doorbal (Anthony Mackie) and ex-convict, Christian bodybuilder Paul Doyle (Dwayne Johnson). Their kidnapping and extortion scheme goes terribly wrong since they have muscles for brains and they're left to haphazardly try to hold onto the elusive American dream.\n\n\n\nIMDBLiNK: &lt;a href=&quot;\nhttp://www.imdb.com/title/tt1980209/&quot; rel=&quot;nofollow&quot; target=&quot;_NEW&quot;&gt;\nhttp://www.imdb.com/title/tt1980209/&lt;/a&gt;\n\n\n\nRELEASENOTES:\n[TITLE]:........................[ Pain &amp; Gain\n[DIRECTOR]:.....................[ Michael Bay\n[RELEASE DATE]:.................[ 26 April 2013 (USA)\n[GENRE]:........................[ Comedy | Crime | Drama\n[NO OF CDs]:....................[ 1\n[FORMAT]:.......................[ Matroska (MKV)\n[FILE SIZE]:....................[ 500MB\n[RESOLUTION]:...................[ 720x288\n[FRAME RATE]:...................[ 29.970 fps\n[LANGUAGE]:.....................[ English\n[SUBTITLES]:....................[ NONE\n[RUNTIME]:......................[ 02:00:52\n[ENCODER]:......................[ ShAaNiG\n[SOURCE]:.......................[ TS-MiLLENiUM\n\n\n\nSCREENSHOTS: &lt;a href=&quot;\nhttp://img802.imageshack.us/img802/975/65485986.jpg&quot; rel=&quot;nofollow&quot; target=&quot;_NEW&quot;&gt;\nhttp://img802.imageshack.us/img802/975/65485986.jpg&lt;/a&gt; &lt;a href=&quot;\nhttp://img850.imageshack.us/img850/6284/61421453.jpg&quot; rel=&quot;nofollow&quot; target=&quot;_NEW&quot;&gt;\nhttp://img850.imageshack.us/img850/6284/61421453.jpg&lt;/a&gt; &lt;a href=&quot;\nhttp://img805.imageshack.us/img805/188/48752296.jpg&quot; rel=&quot;nofollow&quot; target=&quot;_NEW&quot;&gt;\nhttp://img805.imageshack.us/img805/188/48752296.jpg&lt;/a&gt; &lt;a href=&quot;\nhttp://img689.imageshack.us/img689/7310/19092169.jpg&quot; rel=&quot;nofollow&quot; target=&quot;_NEW&quot;&gt;\nhttp://img689.imageshack.us/img689/7310/19092169.jpg&lt;/a&gt; &lt;a href=&quot;\nhttp://img19.imageshack.us/img19/1289/37362283.jpg&quot; rel=&quot;nofollow&quot; target=&quot;_NEW&quot;&gt;\nhttp://img19.imageshack.us/img19/1289/37362283.jpg&lt;/a&gt; &lt;a href=&quot;\nhttp://img41.imageshack.us/img41/5269/48850509.jpg&quot; rel=&quot;nofollow&quot; target=&quot;_NEW&quot;&gt;\nhttp://img41.imageshack.us/img41/5269/48850509.jpg&lt;/a&gt; &lt;a href=&quot;\nhttp://img33.imageshack.us/img33/5052/92598845.jpg&quot; rel=&quot;nofollow&quot; target=&quot;_NEW&quot;&gt;\nhttp://img33.imageshack.us/img33/5052/92598845.jpg&lt;/a&gt; &lt;a href=&quot;\nhttp://img109.imageshack.us/img109/7496/91714102.jpg&quot; rel=&quot;nofollow&quot; target=&quot;_NEW&quot;&gt;\nhttp://img109.imageshack.us/img109/7496/91714102.jpg&lt;/a&gt; &lt;a href=&quot;\nhttp://img571.imageshack.us/img571/7531/35347567.jpg&quot; rel=&quot;nofollow&quot; target=&quot;_NEW&quot;&gt;\nhttp://img571.imageshack.us/img571/7531/35347567.jpg&lt;/a&gt;","torrent":{"xt":"urn:btih:6744dbde127490fe022a9b4b9660402a40e8104f","amp;dn":"Pain+and+Gain+%282013%29+TELESYNC+-+500MB+-+ShAaNiG","amp;tr":["udp%3A%2F%2Ftracker.openbittorrent.com%3A80","udp%3A%2F%2Fopen.demonii.com%3A1337","udp%3A%2F%2Ftracker.coppersurfer.tk%3A6969","udp%3A%2F%2Fexodus.desync.com%3A6969"],"infoHash":"6744dbde127490fe022a9b4b9660402a40e8104f","infoHashBuffer":{"type":"Buffer","data":[103,68,219,222,18,116,144,254,2,42,155,75,150,96,64,42,64,232,16,79]},"announce":[],"urlList":[]}}