{"title":"Tierra de Lobos S03E07 720p HDTV x264-CharlyJerico","uid":9126806,"size":1310297930,"categoryP":"video","categoryS":"hd___tv_shows","magnet":"?xt=urn:btih:7368e9f8dad54fd17605ba2b2e38ce7705be46fe&amp;dn=Tierra+de+Lobos+S03E07+720p+HDTV+x264-CharlyJerico&amp;tr=udp%3A%2F%2Ftracker.openbittorrent.com%3A80&amp;tr=udp%3A%2F%2Fopen.demonii.com%3A1337&amp;tr=udp%3A%2F%2Ftracker.coppersurfer.tk%3A6969&amp;tr=udp%3A%2F%2Fexodus.desync.com%3A6969","seeders":1,"leechers":0,"uploader":"aspras","files":1,"time":1383240475,"description":"English subtitles at thecrisabelpages(dot)blogspot(dot)gr","torrent":{"xt":"urn:btih:7368e9f8dad54fd17605ba2b2e38ce7705be46fe","amp;dn":"Tierra+de+Lobos+S03E07+720p+HDTV+x264-CharlyJerico","amp;tr":["udp%3A%2F%2Ftracker.openbittorrent.com%3A80","udp%3A%2F%2Fopen.demonii.com%3A1337","udp%3A%2F%2Ftracker.coppersurfer.tk%3A6969","udp%3A%2F%2Fexodus.desync.com%3A6969"],"infoHash":"7368e9f8dad54fd17605ba2b2e38ce7705be46fe","infoHashBuffer":{"type":"Buffer","data":[115,104,233,248,218,213,79,209,118,5,186,43,46,56,206,119,5,190,70,254]},"announce":[],"urlList":[]}}