{"title":"Amrapali (1966) - 1/4DvdRip - Hindi - XviD -DUS","uid":5581205,"size":1169336324,"categoryP":"video","categoryS":"movies","magnet":"?xt=urn:btih:76d6dfadfddc2ed85a5e5d8d9e47cb16b45fb970&amp;dn=Amrapali+%281966%29+-+1%2F4DvdRip+-+Hindi+-+XviD+-DUS&amp;tr=udp%3A%2F%2Ftracker.openbittorrent.com%3A80&amp;tr=udp%3A%2F%2Fopen.demonii.com%3A1337&amp;tr=udp%3A%2F%2Ftracker.coppersurfer.tk%3A6969&amp;tr=udp%3A%2F%2Fexodus.desync.com%3A6969","seeders":1,"leechers":0,"uploader":"amanrulz","files":1,"time":1274545403,"description":"mastitorrents.com &lt;a href=&quot;\nhttp://mastitorrents.com/forums/index.php&quot; rel=&quot;nofollow&quot; target=&quot;_NEW&quot;&gt;\nhttp://mastitorrents.com/forums/index.php&lt;/a&gt;\n\n\n----------------------------\nGeneral Information\n----------------------------\nImdb Link............:Click Here\nGenre.................: DRAMA\nRuntime.............: 01:59:00\nVideo Codec.......: XviD MPEG-4\nVideo Bitrate......: 1165kB/s\nResolution..........: 672 x 480\nFPS...................: 29.970\nSource...............: Dvd9@DUS\nAudio Codec.......: MP3\nAudio Bitrate.......: 128 kB/s\nFrequency..........: 44 kHz\n-------------------------------","torrent":{"xt":"urn:btih:76d6dfadfddc2ed85a5e5d8d9e47cb16b45fb970","amp;dn":"Amrapali+%281966%29+-+1%2F4DvdRip+-+Hindi+-+XviD+-DUS","amp;tr":["udp%3A%2F%2Ftracker.openbittorrent.com%3A80","udp%3A%2F%2Fopen.demonii.com%3A1337","udp%3A%2F%2Ftracker.coppersurfer.tk%3A6969","udp%3A%2F%2Fexodus.desync.com%3A6969"],"infoHash":"76d6dfadfddc2ed85a5e5d8d9e47cb16b45fb970","infoHashBuffer":{"type":"Buffer","data":[118,214,223,173,253,220,46,216,90,94,93,141,158,71,203,22,180,95,185,112]},"announce":[],"urlList":[]}}