{"title":"MissionImpossibleII DVDrip(AC3-5.1)DualAudio(Eng-Hindi)-ahl07","uid":5553043,"size":1041864726,"categoryP":"video","categoryS":"movies","magnet":"?xt=urn:btih:8b5aa11103a41b3328995f967f30abc4eab8cf10&amp;dn=MissionImpossibleII+DVDrip%28AC3-5.1%29DualAudio%28Eng-Hindi%29-ahl07&amp;tr=udp%3A%2F%2Ftracker.openbittorrent.com%3A80&amp;tr=udp%3A%2F%2Fopen.demonii.com%3A1337&amp;tr=udp%3A%2F%2Ftracker.coppersurfer.tk%3A6969&amp;tr=udp%3A%2F%2Fexodus.desync.com%3A6969","seeders":1,"leechers":1,"uploader":"ahl07","files":-1,"time":1273595226,"description":"HD DESI ROCKERS GROUP RELEASES\n\n\nINFO:\n\nTitle..................: Mission Impossible 2\nYear...................: 2000 \nGenre..................: Action | Thriller\nDirecter...............: John Woo\nRun time...............: 1h 58mn 29sec\nsize ..................: 993 MB\nLanguages..............: English.Hindi\n\n___________________________________________________________________________\n\nVideo\n\nFormat                           : MKV\nDuration                         : 1h 58mn 29sec\nDisplay aspect ratio             : 16:9\nResolution                       : 648*276\nStream size                      : 724 MiB \n_______________________________________________________________________________\n\n\nAudio #1 :English\nID                               : 1\nFormat                           : AC-3\nDuration                         : 1h 58mn 29sec\nBit rate mode                    : Constant\nBit rate                         : 192 Kbps\nChannel(s)                       : 6 channels\nChannel positions                : Front: L C R, Side: L R, LFE\nSampling rate                    : 48.0 KHz\nStream size                      : 163 MiB \n\n____________________________________________________________________________\n\n\nAudio #2 :Hindi\nID                               : 2\nFormat                           : MPEG 4 Layer 0 \nDuration                         : 1h 58mn 29sec\nBit rate mode                    : Constant\nBit rate                         : 128 Kbps\nChannel(s)                       : 2 channels\nChannel positions                : Front: L R\nSampling rate                    : 48 Hz\nStream size                      : 104 MiB\n__________________________________________________________________________\n\n\n\nSeeding at 2:00 AM ISt - 8:00 AM ISt\nPlease wait during seeding\nPlz seed after download\nThankyou...\n\nScreens\n &lt;a href=&quot;\nhttp://img684.imageshack.us/img684/6595/15182724.jpg&quot; rel=&quot;nofollow&quot; target=&quot;_NEW&quot;&gt;\nhttp://img684.imageshack.us/img684/6595/15182724.jpg&lt;/a&gt; &lt;a href=&quot;\nhttp://img193.imageshack.us/img193/1725/13368637.jpg&quot; rel=&quot;nofollow&quot; target=&quot;_NEW&quot;&gt;\nhttp://img193.imageshack.us/img193/1725/13368637.jpg&lt;/a&gt; &lt;a href=&quot;\nhttp://img406.imageshack.us/img406/1984/27973412.jpg&quot; rel=&quot;nofollow&quot; target=&quot;_NEW&quot;&gt;\nhttp://img406.imageshack.us/img406/1984/27973412.jpg&lt;/a&gt; &lt;a href=&quot;\nhttp://img9.imageshack.us/img9/2742/52091426.jpg&quot; rel=&quot;nofollow&quot; target=&quot;_NEW&quot;&gt;\nhttp://img9.imageshack.us/img9/2742/52091426.jpg&lt;/a&gt; &lt;a href=&quot;\nhttp://img98.imageshack.us/img98/6651/51270266.jpg&quot; rel=&quot;nofollow&quot; target=&quot;_NEW&quot;&gt;\nhttp://img98.imageshack.us/img98/6651/51270266.jpg&lt;/a&gt;","torrent":{"xt":"urn:btih:8b5aa11103a41b3328995f967f30abc4eab8cf10","amp;dn":"MissionImpossibleII+DVDrip%28AC3-5.1%29DualAudio%28Eng-Hindi%29-ahl07","amp;tr":["udp%3A%2F%2Ftracker.openbittorrent.com%3A80","udp%3A%2F%2Fopen.demonii.com%3A1337","udp%3A%2F%2Ftracker.coppersurfer.tk%3A6969","udp%3A%2F%2Fexodus.desync.com%3A6969"],"infoHash":"8b5aa11103a41b3328995f967f30abc4eab8cf10","infoHashBuffer":{"type":"Buffer","data":[139,90,161,17,3,164,27,51,40,153,95,150,127,48,171,196,234,184,207,16]},"announce":[],"urlList":[]}}