{"title":"[StepSiblingsCaught] Molly Mae (Step Sister Fucks Step Brother A","uid":14037133,"size":247810187,"categoryP":"porn","categoryS":"movie_clips","magnet":"?xt=urn:btih:965554b22e53472d1e6c140079a9b7541945a342&amp;dn=%5BStepSiblingsCaught%5D+Molly+Mae+%28Step+Sister+Fucks+Step+Brother+A&amp;tr=udp%3A%2F%2Ftracker.leechers-paradise.org%3A6969&amp;tr=udp%3A%2F%2Fzer0day.ch%3A1337&amp;tr=udp%3A%2F%2Fopen.demonii.com%3A1337&amp;tr=udp%3A%2F%2Ftracker.coppersurfer.tk%3A6969&amp;tr=udp%3A%2F%2Fexodus.desync.com%3A6969","seeders":1,"leechers":0,"uploader":"KayWily","files":1,"time":1458980068,"description":"[StepSiblingsCaught] Molly Mae (Step Sister Fucks Step Brother And Friend - 26.03.16)\r\n\r\n \nhttp://porn-harbor.com/image/NWj","torrent":{"xt":"urn:btih:965554b22e53472d1e6c140079a9b7541945a342","amp;dn":"%5BStepSiblingsCaught%5D+Molly+Mae+%28Step+Sister+Fucks+Step+Brother+A","amp;tr":["udp%3A%2F%2Ftracker.leechers-paradise.org%3A6969","udp%3A%2F%2Fzer0day.ch%3A1337","udp%3A%2F%2Fopen.demonii.com%3A1337","udp%3A%2F%2Ftracker.coppersurfer.tk%3A6969","udp%3A%2F%2Fexodus.desync.com%3A6969"],"infoHash":"965554b22e53472d1e6c140079a9b7541945a342","infoHashBuffer":{"type":"Buffer","data":[150,85,84,178,46,83,71,45,30,108,20,0,121,169,183,84,25,69,163,66]},"announce":[],"urlList":[]}}