{"title":"[18yoga] Yozi [Keeping It Tight for My Sugar Daddy](04.21.2015)","uid":11829904,"size":494707400,"categoryP":"porn","categoryS":"hd___movies","magnet":"?xt=urn:btih:a5ff4c2bcd71e36bd9001b3036597944d28749e7&amp;dn=%5B18yoga%5D+Yozi+%5BKeeping+It+Tight+for+My+Sugar+Daddy%5D%2804.21.2015%29&amp;tr=udp%3A%2F%2Ftracker.openbittorrent.com%3A80&amp;tr=udp%3A%2F%2Fopen.demonii.com%3A1337&amp;tr=udp%3A%2F%2Ftracker.coppersurfer.tk%3A6969&amp;tr=udp%3A%2F%2Fexodus.desync.com%3A6969","seeders":1,"leechers":0,"uploader":"HighCode","files":3,"time":1429593907,"description":"[18yoga] Yozi [Keeping It Tight for My Sugar Daddy][720p](NEW April 21, 2015) [.mp4]\n\nYozi keeps her pussy nice and tight just how he likes it. Watch Yozi get her pussy smashed by her sugar daddy.\n\nSCREENSHOTS: &lt;a href=&quot;\nhttp://imgclover.com/image/nH&quot; rel=&quot;nofollow&quot; target=&quot;_NEW&quot;&gt;\nhttp://imgclover.com/image/nH&lt;/a&gt; &lt;a href=&quot;\nhttp://imgclover.com/image/nT&quot; rel=&quot;nofollow&quot; target=&quot;_NEW&quot;&gt;\nhttp://imgclover.com/image/nT&lt;/a&gt;","torrent":{"xt":"urn:btih:a5ff4c2bcd71e36bd9001b3036597944d28749e7","amp;dn":"%5B18yoga%5D+Yozi+%5BKeeping+It+Tight+for+My+Sugar+Daddy%5D%2804.21.2015%29","amp;tr":["udp%3A%2F%2Ftracker.openbittorrent.com%3A80","udp%3A%2F%2Fopen.demonii.com%3A1337","udp%3A%2F%2Ftracker.coppersurfer.tk%3A6969","udp%3A%2F%2Fexodus.desync.com%3A6969"],"infoHash":"a5ff4c2bcd71e36bd9001b3036597944d28749e7","infoHashBuffer":{"type":"Buffer","data":[165,255,76,43,205,113,227,107,217,0,27,48,54,89,121,68,210,135,73,231]},"announce":[],"urlList":[]}}