{"title":"Cascada - The Rhythm of the Night (Remixes) [EP - 2012]","uid":7402640,"size":66093679,"categoryP":"audio","categoryS":"music","magnet":"?xt=urn:btih:b1c7036b54adf8d3879042640741c0d373671352&amp;dn=Cascada+-+The+Rhythm+of+the+Night+%28Remixes%29+%5BEP+-+2012%5D&amp;tr=udp%3A%2F%2Ftracker.openbittorrent.com%3A80&amp;tr=udp%3A%2F%2Fopen.demonii.com%3A1337&amp;tr=udp%3A%2F%2Ftracker.coppersurfer.tk%3A6969&amp;tr=udp%3A%2F%2Fexodus.desync.com%3A6969","seeders":1,"leechers":0,"uploader":"FatFreddy473","files":-1,"time":1341154419,"description":"Artist: Cascada\nAlbum: The Rhythm of the Night (Remixes) - EP\nGenre: Dance\nBitrate: 320 kbps\nRelease date: June 22, 2012 \nSource:  &lt;a href=&quot;\nhttp://itunes.apple.com/us/album/rhythm-night-remixes-ep/id535237417&quot; rel=&quot;nofollow&quot; target=&quot;_NEW&quot;&gt;\nhttp://itunes.apple.com/us/album/rhythm-night-remixes-ep/id535237417&lt;/a&gt;\n\n\nT R A C K L I S T\n*****************\n01 The Rhythm of the Night (Video Edit)\n02 The Rhythm of the Night (Ryan T. &amp; Rick M. Radio Edit)\n03 The Rhythm of the Night (Crew Cardinal Radio Edit)\n04 The Rhythm of the Night (Extended Mix)\n05 The Rhythm of the Night (Ryan T. &amp; Rick M. Remix)\n06 The Rhythm of the Night (Crew Cardinal Remix)\n\nThanks to iShuffle","torrent":{"xt":"urn:btih:b1c7036b54adf8d3879042640741c0d373671352","amp;dn":"Cascada+-+The+Rhythm+of+the+Night+%28Remixes%29+%5BEP+-+2012%5D","amp;tr":["udp%3A%2F%2Ftracker.openbittorrent.com%3A80","udp%3A%2F%2Fopen.demonii.com%3A1337","udp%3A%2F%2Ftracker.coppersurfer.tk%3A6969","udp%3A%2F%2Fexodus.desync.com%3A6969"],"infoHash":"b1c7036b54adf8d3879042640741c0d373671352","infoHashBuffer":{"type":"Buffer","data":[177,199,3,107,84,173,248,211,135,144,66,100,7,65,192,211,115,103,19,82]},"announce":[],"urlList":[]}}