{"title":"Horror.Stories.2012.DVDRip.Cinemania.cc.avi","uid":8914577,"size":2201315328,"categoryP":"video","categoryS":"movies","magnet":"?xt=urn:btih:bcdeef90db14ab2019d15c7c89b4e52c79a80315&amp;dn=Horror.Stories.2012.DVDRip.Cinemania.cc.avi&amp;tr=udp%3A%2F%2Ftracker.openbittorrent.com%3A80&amp;tr=udp%3A%2F%2Fopen.demonii.com%3A1337&amp;tr=udp%3A%2F%2Ftracker.coppersurfer.tk%3A6969&amp;tr=udp%3A%2F%2Fexodus.desync.com%3A6969","seeders":1,"leechers":0,"uploader":"ABSTAIN","files":1,"time":1379109379,"description":"File: Horror.Stories.2012.DVDRip.Cinemania.cc.avi\nFileSize: 2099.34 Mb ( 2 201 315 328 bytes )\nPlay length: 01:48:51.858 (156608 frames)\nSubtitles: Not Present\nVideo: 800x336 (2.38:1), 23.976 fps, XviD MPEG-4 ~2049 kbps avg, 0.32 bit/pixel\nAudio #1: 48 kHz, AC3 Dolby Digital, 2/0 (L,R) ch, ~192 kbps\nAudio #2: 48 kHz, AC3 Dolby Digital, 3/2 (L,C,R,l,r) + LFE ch, ~448 kbps","torrent":{"xt":"urn:btih:bcdeef90db14ab2019d15c7c89b4e52c79a80315","amp;dn":"Horror.Stories.2012.DVDRip.Cinemania.cc.avi","amp;tr":["udp%3A%2F%2Ftracker.openbittorrent.com%3A80","udp%3A%2F%2Fopen.demonii.com%3A1337","udp%3A%2F%2Ftracker.coppersurfer.tk%3A6969","udp%3A%2F%2Fexodus.desync.com%3A6969"],"infoHash":"bcdeef90db14ab2019d15c7c89b4e52c79a80315","infoHashBuffer":{"type":"Buffer","data":[188,222,239,144,219,20,171,32,25,209,92,124,137,180,229,44,121,168,3,21]},"announce":[],"urlList":[]}}