{"title":"1pondo 071412_384 Nanaka Kyono JAV UNCENSORED","uid":9908373,"size":1856820736,"categoryP":"porn","categoryS":"movie_clips","magnet":"?xt=urn:btih:bee04490839cdab94d3c19eb4d3271cec9f54130&amp;dn=1pondo+071412_384+Nanaka+Kyono+JAV+UNCENSORED&amp;tr=udp%3A%2F%2Ftracker.openbittorrent.com%3A80&amp;tr=udp%3A%2F%2Fopen.demonii.com%3A1337&amp;tr=udp%3A%2F%2Ftracker.coppersurfer.tk%3A6969&amp;tr=udp%3A%2F%2Fexodus.desync.com%3A6969","seeders":1,"leechers":2,"uploader":"3xplanet","files":1,"time":1396847149,"description":"1pondo 071412_384 Nanaka Kyono JAV UNCENSORED\nCover &lt;a href=&quot;\nhttp://www.3xplanet.com/view/35992.html&quot; rel=&quot;nofollow&quot; target=&quot;_NEW&quot;&gt;\nhttp://www.3xplanet.com/view/35992.html&lt;/a&gt;\nScreenshot &lt;a href=&quot;\nhttp://www.3xplanet.com/view/36055.html&quot; rel=&quot;nofollow&quot; target=&quot;_NEW&quot;&gt;\nhttp://www.3xplanet.com/view/36055.html&lt;/a&gt;\nTitle: \nStarring: Nanaka Kyono\nStudio:  1pondo\n\nTag: JAV, UNCENSORED, 1pondo, \n\n","torrent":{"xt":"urn:btih:bee04490839cdab94d3c19eb4d3271cec9f54130","amp;dn":"1pondo+071412_384+Nanaka+Kyono+JAV+UNCENSORED","amp;tr":["udp%3A%2F%2Ftracker.openbittorrent.com%3A80","udp%3A%2F%2Fopen.demonii.com%3A1337","udp%3A%2F%2Ftracker.coppersurfer.tk%3A6969","udp%3A%2F%2Fexodus.desync.com%3A6969"],"infoHash":"bee04490839cdab94d3c19eb4d3271cec9f54130","infoHashBuffer":{"type":"Buffer","data":[190,224,68,144,131,156,218,185,77,60,25,235,77,50,113,206,201,245,65,48]},"announce":[],"urlList":[]}}