{"title":"MC Lars - The Edgar Allan Poe EP 320 kb/s","uid":9688462,"size":92423593,"categoryP":"audio","categoryS":"music","magnet":"?xt=urn:btih:c832a8dd170aa8c8565273c6c8c889d22f77f86e&amp;dn=MC+Lars+-+The+Edgar+Allan+Poe+EP+320+kb%2Fs&amp;tr=udp%3A%2F%2Ftracker.openbittorrent.com%3A80&amp;tr=udp%3A%2F%2Fopen.demonii.com%3A1337&amp;tr=udp%3A%2F%2Ftracker.coppersurfer.tk%3A6969&amp;tr=udp%3A%2F%2Fexodus.desync.com%3A6969","seeders":1,"leechers":1,"uploader":"Vakume","files":-1,"time":1393817357,"description":"                     MC LARS EDGAR ALLAN POE EP BANDCAMP RIP \n                             320 kb/s Bitrate Quality\n\n\n\n\n\n01 - Flow Like Poe\n02 - The Tell-Tale &lt;3 (feat. Random)\n03 - Lenore (I Miss You)\n04 - (Rock) the Bells\n05 - Annabel Lee R.I.P. (2012)(feat. Common Rotation)\n06 - The Abridged Narrative of Arthur Gordon Pym of Nantucket\n07 - Mr. Raven (2012)(feat. The Dead Milkmen)\n08 - Annabel Lee R.I.P. (DREAMTRAK Remix)\n09 - Flow Like Somebody in Rack City That I Used to Know (Wait What's Gotyga Mashup)\n10 - Annabel Lee R.I.P.\n11 - Mr. Raven\n\n\n\n\nRequests? tell me! comment!","torrent":{"xt":"urn:btih:c832a8dd170aa8c8565273c6c8c889d22f77f86e","amp;dn":"MC+Lars+-+The+Edgar+Allan+Poe+EP+320+kb%2Fs","amp;tr":["udp%3A%2F%2Ftracker.openbittorrent.com%3A80","udp%3A%2F%2Fopen.demonii.com%3A1337","udp%3A%2F%2Ftracker.coppersurfer.tk%3A6969","udp%3A%2F%2Fexodus.desync.com%3A6969"],"infoHash":"c832a8dd170aa8c8565273c6c8c889d22f77f86e","infoHashBuffer":{"type":"Buffer","data":[200,50,168,221,23,10,168,200,86,82,115,198,200,200,137,210,47,119,248,110]},"announce":[],"urlList":[]}}