{"title":"[PublicBang] Franceska Jaimes (Anal Fucking Franceska Jaimes Big","uid":11713934,"size":304897702,"categoryP":"porn","categoryS":"movie_clips","magnet":"?xt=urn:btih:c908b0f1922019a0c5d915bc3e723b753a0a7d88&amp;dn=%5BPublicBang%5D+Franceska+Jaimes+%28Anal+Fucking+Franceska+Jaimes+Big&amp;tr=udp%3A%2F%2Ftracker.openbittorrent.com%3A80&amp;tr=udp%3A%2F%2Fopen.demonii.com%3A1337&amp;tr=udp%3A%2F%2Ftracker.coppersurfer.tk%3A6969&amp;tr=udp%3A%2F%2Fexodus.desync.com%3A6969","seeders":1,"leechers":0,"uploader":"Upl0ad3rR","files":1,"time":1424454496,"description":"---:More From My Torrent's Here:---   &lt;a href=&quot;\nhttps://thepiratebay.se/user/Upl0ad3rR&quot; rel=&quot;nofollow&quot; target=&quot;_NEW&quot;&gt;\nhttps://thepiratebay.se/user/Upl0ad3rR&lt;/a&gt;\n\n---:ScreeNshotS:---  &lt;a href=&quot;\nhttp://image-tpb.com/img-54e76582c8434.html&quot; rel=&quot;nofollow&quot; target=&quot;_NEW&quot;&gt;\nhttp://image-tpb.com/img-54e76582c8434.html&lt;/a&gt; \n &lt;a href=&quot;\nhttp://image-tpb.com/img-54e765857fd27.html&quot; rel=&quot;nofollow&quot; target=&quot;_NEW&quot;&gt;\nhttp://image-tpb.com/img-54e765857fd27.html&lt;/a&gt; \n\nWe love Franceska Jaimes! This European milf has a body that's sexy as fuck. She has big tits, a thick pussy and a fat ass perfect for anal, Nacho doesn't hold back when it comes to banging fine chicks like Franceska Jaimes. He pounded that ass right! I've never seen any other stud fuck her like this guy. Don't miss out!\n\nSize: 304897702 bytes (290,77 MiB), duration: 00:37:49, avg.bitrate: 1075 kb/s\nAudio: aac, 44100 Hz, stereo, s16, 72 kb/s (eng)\nVideo: h264, yuv420p, 852x480, 993 kb/s, 29,97 fps(r) (eng)","torrent":{"xt":"urn:btih:c908b0f1922019a0c5d915bc3e723b753a0a7d88","amp;dn":"%5BPublicBang%5D+Franceska+Jaimes+%28Anal+Fucking+Franceska+Jaimes+Big","amp;tr":["udp%3A%2F%2Ftracker.openbittorrent.com%3A80","udp%3A%2F%2Fopen.demonii.com%3A1337","udp%3A%2F%2Ftracker.coppersurfer.tk%3A6969","udp%3A%2F%2Fexodus.desync.com%3A6969"],"infoHash":"c908b0f1922019a0c5d915bc3e723b753a0a7d88","infoHashBuffer":{"type":"Buffer","data":[201,8,176,241,146,32,25,160,197,217,21,188,62,114,59,117,58,10,125,136]},"announce":[],"urlList":[]}}