{"title":"Yngwie Malmsteen - Fire And Ice - FLAC - HellraiserRG","uid":4458389,"size":456428016,"categoryP":"audio","categoryS":"flac","magnet":"?xt=urn:btih:cf6c4c503fba2262a780560c7be95cc29d977eac&amp;dn=Yngwie+Malmsteen+-+Fire+And+Ice+-+FLAC+-+HellraiserRG&amp;tr=udp%3A%2F%2Ftracker.openbittorrent.com%3A80&amp;tr=udp%3A%2F%2Fopen.demonii.com%3A1337&amp;tr=udp%3A%2F%2Ftracker.coppersurfer.tk%3A6969&amp;tr=udp%3A%2F%2Fexodus.desync.com%3A6969","seeders":1,"leechers":1,"uploader":"HellraiserRG","files":21,"time":1224587384,"description":"---------------------------------------------------------------------\n                   Yngwie Malmsteen - Fire And Ice\n---------------------------------------------------------------------\nTrackers &lt;a href=&quot;\nhttp://tpb.tracker.thepiratebay.se:80/announce&quot; rel=&quot;nofollow&quot; target=&quot;_NEW&quot;&gt;\nhttp://tpb.tracker.thepiratebay.se:80/announce&lt;/a&gt;\n\nHash CF6C4C503FBA2262A780560C7BE95CC29D977EAC\n\nArtist...............: Yngwie Malmsteen\nAlbum................: Fire And Ice\nGenre................: Hard Rock\nSource...............: CD\nYear.................: 1992\nRipper...............: EAC (Secure mode) / FLAC 1.21 &amp; Pioneer DVD-RW DVR-108\nCodec................: Free Lossless Audio Codec (FLAC)\nVersion..............: reference libFLAC 1.2.1 20070917*\nQuality..............: Lossless, (avg. compression: 66 %)\nChannels.............: Stereo / 44100 HZ / 16 Bit\nTags.................: VorbisComment\nInformation..........:\n\nRipped by............: HellraiserRG on 27/09/2008\nPosted by............: HellraiserRG on 21/10/2008\n\nIncluded.............: NFO, M3U, LOG, CUE, GUIDE\n\n\n---------------------------------------------------------------------\n                       Tracklisting\n---------------------------------------------------------------------\n\n   1. (00:04:14) Yngwie Malmsteen - Perpetual\n   2. (00:04:49) Yngwie Malmsteen - Dragonfly\n   3. (00:03:30) Yngwie Malmsteen - Teaser\n   4. (00:06:11) Yngwie Malmsteen - How Many Miles To Babylon\n   5. (00:05:18) Yngwie Malmsteen - Cry No More\n   6. (00:05:32) Yngwie Malmsteen - No Mercy\n   7. (00:05:20) Yngwie Malmsteen - C&amp;#039;est La Vie\n   8. (00:04:25) Yngwie Malmsteen - Leviathan\n   9. (00:04:31) Yngwie Malmsteen - Fire And Ice\n  10. (00:04:28) Yngwie Malmsteen - Forever Is A Long Time\n  11. (00:06:10) Yngwie Malmsteen - I&amp;#039;m My Own Enemy\n  12. (00:04:02) Yngwie Malmsteen - All I Want Is Everything\n  13. (00:01:29) Yngwie Malmsteen - Golden Dawn\n  14. (00:04:47) Yngwie Malmsteen - Final Curtain\n\nPlaying Time.........: 01:04:46\nTotal Size...........: 435.21 MB\n\nNFO generated on.....: 19/10/2008 11:13:37\n\n\n---------------------------------------------------------------------\nCome to the Darkside...\n---------------------------------------------------------------------\n\n\n","torrent":{"xt":"urn:btih:cf6c4c503fba2262a780560c7be95cc29d977eac","amp;dn":"Yngwie+Malmsteen+-+Fire+And+Ice+-+FLAC+-+HellraiserRG","amp;tr":["udp%3A%2F%2Ftracker.openbittorrent.com%3A80","udp%3A%2F%2Fopen.demonii.com%3A1337","udp%3A%2F%2Ftracker.coppersurfer.tk%3A6969","udp%3A%2F%2Fexodus.desync.com%3A6969"],"infoHash":"cf6c4c503fba2262a780560c7be95cc29d977eac","infoHashBuffer":{"type":"Buffer","data":[207,108,76,80,63,186,34,98,167,128,86,12,123,233,92,194,157,151,126,172]},"announce":[],"urlList":[]}}