{"title":"Glory Hole - Riley Reid HD 720p","uid":8488339,"size":567862227,"categoryP":"porn","categoryS":"hd___movies","magnet":"?xt=urn:btih:dfb0e0726d100133eb629367750c8f39df8bf81f&amp;dn=Glory+Hole+-+Riley+Reid+HD+720p&amp;tr=udp%3A%2F%2Ftracker.openbittorrent.com%3A80&amp;tr=udp%3A%2F%2Fopen.demonii.com%3A1337&amp;tr=udp%3A%2F%2Ftracker.coppersurfer.tk%3A6969&amp;tr=udp%3A%2F%2Fexodus.desync.com%3A6969","seeders":1,"leechers":0,"uploader":"irealu69","files":-1,"time":1368934146,"description":"Glory Hole - Riley Reid HD 720p\n~~~~~~~~~~~~~~~~~~~~~~~~~~~~~~~\n\nScreenshots:\n~~~~~~~~~~~~\n &lt;a href=&quot;\nhttp://picturevip.com/x/clean/m6t&quot; rel=&quot;nofollow&quot; target=&quot;_NEW&quot;&gt;\nhttp://picturevip.com/x/clean/m6t&lt;/a&gt;\n &lt;a href=&quot;\nhttp://picturevip.com/x/clean/m61&quot; rel=&quot;nofollow&quot; target=&quot;_NEW&quot;&gt;\nhttp://picturevip.com/x/clean/m61&lt;/a&gt;\n &lt;a href=&quot;\nhttp://picturevip.com/x/clean/m64&quot; rel=&quot;nofollow&quot; target=&quot;_NEW&quot;&gt;\nhttp://picturevip.com/x/clean/m64&lt;/a&gt;\n &lt;a href=&quot;\nhttp://picturevip.com/x/clean/m6Y&quot; rel=&quot;nofollow&quot; target=&quot;_NEW&quot;&gt;\nhttp://picturevip.com/x/clean/m6Y&lt;/a&gt;\n\n\nVideos Info:\n~~~~~~~~~~~~\nSize: 541.56 MB\nDuration: 23:41\nResolution: 1280x720","torrent":{"xt":"urn:btih:dfb0e0726d100133eb629367750c8f39df8bf81f","amp;dn":"Glory+Hole+-+Riley+Reid+HD+720p","amp;tr":["udp%3A%2F%2Ftracker.openbittorrent.com%3A80","udp%3A%2F%2Fopen.demonii.com%3A1337","udp%3A%2F%2Ftracker.coppersurfer.tk%3A6969","udp%3A%2F%2Fexodus.desync.com%3A6969"],"infoHash":"dfb0e0726d100133eb629367750c8f39df8bf81f","infoHashBuffer":{"type":"Buffer","data":[223,176,224,114,109,16,1,51,235,98,147,103,117,12,143,57,223,139,248,31]},"announce":[],"urlList":[]}}