{"title":"Against the Wild 2013 1080p BluRay x264 MELiTE DUAL","uid":11381396,"size":6950187440,"categoryP":"video","categoryS":"hd___movies","magnet":"?xt=urn:btih:dfc5fadf83a59fc67bad8b0bec745b5d2381c877&amp;dn=Against+the+Wild+2013+1080p+BluRay+x264+MELiTE+DUAL&amp;tr=udp%3A%2F%2Ftracker.openbittorrent.com%3A80&amp;tr=udp%3A%2F%2Fopen.demonii.com%3A1337&amp;tr=udp%3A%2F%2Ftracker.coppersurfer.tk%3A6969&amp;tr=udp%3A%2F%2Fexodus.desync.com%3A6969","seeders":1,"leechers":2,"uploader":"Alemao99","files":3,"time":1415218904,"description":"Zach and Hannah, two children and their dog, a Husky named Chinook, after suffering a plane crash where the pilot died, must struggle to survive in a wild and frightening environment. Meanwhile her mother drives her search. \n\nTitle: An Animal Adventure \nOriginal Title: Against the Wild \nDirector: Richard Boddington \nRelease: 2013 \nDuration: 1 hour and 32 minutes \nGenre: Adventure / Family \nImdb: http://www.imdb.com/title/tt2475846/ \n\nSize: 6:47 GB \nFile extension: .MKV \nVideo Quality: Bluray \nVideo codec: H.264 / AVC \nAudio Codec: AC3 5.1 \nResolution: 1920 x 1080 \nAudio Language: Portuguese / English \nSubtitles: Portuguese \n\ni.imgur.com/hLzgZ62.jpg \ni.imgur.com/JZ1u9xk.jpg\n\n\nSEED PLEASE\n\nENJOY","torrent":{"xt":"urn:btih:dfc5fadf83a59fc67bad8b0bec745b5d2381c877","amp;dn":"Against+the+Wild+2013+1080p+BluRay+x264+MELiTE+DUAL","amp;tr":["udp%3A%2F%2Ftracker.openbittorrent.com%3A80","udp%3A%2F%2Fopen.demonii.com%3A1337","udp%3A%2F%2Ftracker.coppersurfer.tk%3A6969","udp%3A%2F%2Fexodus.desync.com%3A6969"],"infoHash":"dfc5fadf83a59fc67bad8b0bec745b5d2381c877","infoHashBuffer":{"type":"Buffer","data":[223,197,250,223,131,165,159,198,123,173,139,11,236,116,91,93,35,129,200,119]},"announce":[],"urlList":[]}}