{"title":"Fat Girl 2001 BluRay Criterion Collection 720p DTS x264-CHD","uid":6487693,"size":5415159090,"categoryP":"video","categoryS":"hd___movies","magnet":"?xt=urn:btih:e70c5e5c6ec7e3bf690a9113f5def19aeed49669&amp;dn=Fat+Girl+2001+BluRay+Criterion+Collection+720p+DTS+x264-CHD&amp;tr=udp%3A%2F%2Ftracker.openbittorrent.com%3A80&amp;tr=udp%3A%2F%2Fopen.demonii.com%3A1337&amp;tr=udp%3A%2F%2Ftracker.coppersurfer.tk%3A6969&amp;tr=udp%3A%2F%2Fexodus.desync.com%3A6969","seeders":1,"leechers":0,"uploader":"TPBAgri","files":-1,"time":1308763059,"description":"Fat.Girl.2001.BluRay.Criterion.Collection.720p.DTS.x264-CHD\n\n\nRELEASE DATE....: 05/20/2011\nTHEATRE DATE....: 03/07/2001\n\niMDB URL........: http://www.imdb.com/title/tt0243255/\niMDB RATiNG.....: 6.4/10 (4,432 votes)\nGENRE...........: Drama\nSOURCE .........: Blu-Ray Criterion Collection 1080p AVC DTS-HD MA5.1-CHDBits\nViDEO BiTRATE...: x264 @ 6755 Kbps\nFRAME RATE......: 23.976 fps\nAUDiO BiTRATE...: DTS @ 1509 Kbps\nRUNTiME.........: 87 mins\nASPECT RATiO....: 1.86 : 1\nRESOLUTiON......: 1280 x 688\nLANGUAGE........: French\nSUBTiTLES.......: None\nFilE SiZE.......: 5,240,544 KB\nENCODER.........: redthorm@CHD","torrent":{"xt":"urn:btih:e70c5e5c6ec7e3bf690a9113f5def19aeed49669","amp;dn":"Fat+Girl+2001+BluRay+Criterion+Collection+720p+DTS+x264-CHD","amp;tr":["udp%3A%2F%2Ftracker.openbittorrent.com%3A80","udp%3A%2F%2Fopen.demonii.com%3A1337","udp%3A%2F%2Ftracker.coppersurfer.tk%3A6969","udp%3A%2F%2Fexodus.desync.com%3A6969"],"infoHash":"e70c5e5c6ec7e3bf690a9113f5def19aeed49669","infoHashBuffer":{"type":"Buffer","data":[231,12,94,92,110,199,227,191,105,10,145,19,245,222,241,154,238,212,150,105]},"announce":[],"urlList":[]}}