{"title":"TeenFidelity Sophia Leone Bad Neighbor 2 XXX 16.06.29","uid":15176595,"size":393532818,"categoryP":"porn","categoryS":"movie_clips","magnet":"?xt=urn:btih:ec635c0eebe4f52af317f5226e370b1667971179&amp;dn=TeenFidelity+Sophia+Leone+Bad+Neighbor+2+XXX+16.06.29&amp;tr=udp%3A%2F%2Ftracker.leechers-paradise.org%3A6969&amp;tr=udp%3A%2F%2Fzer0day.ch%3A1337&amp;tr=udp%3A%2F%2Fopen.demonii.com%3A1337&amp;tr=udp%3A%2F%2Ftracker.coppersurfer.tk%3A6969&amp;tr=udp%3A%2F%2Fexodus.desync.com%3A6969","seeders":1,"leechers":0,"uploader":"thfatboys","files":1,"time":1467425154,"description":"Screens: \nhttp://imgpeak.com/img-5776d218bd169.html","torrent":{"xt":"urn:btih:ec635c0eebe4f52af317f5226e370b1667971179","amp;dn":"TeenFidelity+Sophia+Leone+Bad+Neighbor+2+XXX+16.06.29","amp;tr":["udp%3A%2F%2Ftracker.leechers-paradise.org%3A6969","udp%3A%2F%2Fzer0day.ch%3A1337","udp%3A%2F%2Fopen.demonii.com%3A1337","udp%3A%2F%2Ftracker.coppersurfer.tk%3A6969","udp%3A%2F%2Fexodus.desync.com%3A6969"],"infoHash":"ec635c0eebe4f52af317f5226e370b1667971179","infoHashBuffer":{"type":"Buffer","data":[236,99,92,14,235,228,245,42,243,23,245,34,110,55,11,22,103,151,17,121]},"announce":[],"urlList":[]}}