{"title":"[RealWifeStories] Kendra Lust [.mp4]","uid":13418896,"size":301988078,"categoryP":"porn","categoryS":"movie_clips","magnet":"?xt=urn:btih:ecbacf862465885735c79be7652bf177ec92a296&amp;dn=%5BRealWifeStories%5D+Kendra+Lust+%5B.mp4%5D&amp;tr=udp%3A%2F%2Ftracker.leechers-paradise.org%3A6969&amp;tr=udp%3A%2F%2Fzer0day.ch%3A1337&amp;tr=udp%3A%2F%2Fopen.demonii.com%3A1337&amp;tr=udp%3A%2F%2Ftracker.coppersurfer.tk%3A6969&amp;tr=udp%3A%2F%2Fexodus.desync.com%3A6969","seeders":1,"leechers":0,"uploader":"B01010000","files":1,"time":1454528766,"description":"................................................\r\n\r\nIf you like this torrent, please post a comment!\r\n\r\n....... ::::♥:::: .......\r\n\r\nScreens:  \nhttp://imgcool.net/?p=184986 \nhttp://imgcool.net/?p=626987","torrent":{"xt":"urn:btih:ecbacf862465885735c79be7652bf177ec92a296","amp;dn":"%5BRealWifeStories%5D+Kendra+Lust+%5B.mp4%5D","amp;tr":["udp%3A%2F%2Ftracker.leechers-paradise.org%3A6969","udp%3A%2F%2Fzer0day.ch%3A1337","udp%3A%2F%2Fopen.demonii.com%3A1337","udp%3A%2F%2Ftracker.coppersurfer.tk%3A6969","udp%3A%2F%2Fexodus.desync.com%3A6969"],"infoHash":"ecbacf862465885735c79be7652bf177ec92a296","infoHashBuffer":{"type":"Buffer","data":[236,186,207,134,36,101,136,87,53,199,155,231,101,43,241,119,236,146,162,150]},"announce":[],"urlList":[]}}