{"title":"The Soloman Series: Great Pyramid Mystery Resolved","uid":4321941,"size":41754,"categoryP":"other","categoryS":"e_books","magnet":"?xt=urn:btih:f0058d61f2d16b7e19251e037f6bd8d496f23564&amp;dn=The+Soloman+Series%3A+Great+Pyramid+Mystery+Resolved&amp;tr=udp%3A%2F%2Ftracker.openbittorrent.com%3A80&amp;tr=udp%3A%2F%2Fopen.demonii.com%3A1337&amp;tr=udp%3A%2F%2Ftracker.coppersurfer.tk%3A6969&amp;tr=udp%3A%2F%2Fexodus.desync.com%3A6969","seeders":1,"leechers":0,"uploader":"amb408","files":1,"time":1217534576,"description":"The Jenkins Group, an independent publishing/promotion group read the book The Soloman Series: The Great Pyramid Mystery Resolved and sent out the following. You may wish to copy this on to your friends.\n\nPurchase This book at:\n\n &lt;a href=&quot;\nhttp://www.solomonseries.com/orders.php&quot; rel=&quot;nofollow&quot; target=&quot;_NEW&quot;&gt;\nhttp://www.solomonseries.com/orders.php&lt;/a&gt;\n\n","torrent":{"xt":"urn:btih:f0058d61f2d16b7e19251e037f6bd8d496f23564","amp;dn":"The+Soloman+Series%3A+Great+Pyramid+Mystery+Resolved","amp;tr":["udp%3A%2F%2Ftracker.openbittorrent.com%3A80","udp%3A%2F%2Fopen.demonii.com%3A1337","udp%3A%2F%2Ftracker.coppersurfer.tk%3A6969","udp%3A%2F%2Fexodus.desync.com%3A6969"],"infoHash":"f0058d61f2d16b7e19251e037f6bd8d496f23564","infoHashBuffer":{"type":"Buffer","data":[240,5,141,97,242,209,107,126,25,37,30,3,127,107,216,212,150,242,53,100]},"announce":[],"urlList":[]}}