{"title":"Pervert Desi Indian Housewife","uid":12913806,"size":128520803,"categoryP":"porn","categoryS":"movie_clips","magnet":"?xt=urn:btih:fc6c80867debcda85a88e7707b7ce729fd976456&amp;dn=Pervert+Desi+Indian+Housewife&amp;tr=udp%3A%2F%2Ftracker.leechers-paradise.org%3A6969&amp;tr=udp%3A%2F%2Fzer0day.ch%3A1337&amp;tr=udp%3A%2F%2Fopen.demonii.com%3A1337&amp;tr=udp%3A%2F%2Ftracker.coppersurfer.tk%3A6969&amp;tr=udp%3A%2F%2Fexodus.desync.com%3A6969","seeders":1,"leechers":0,"uploader":"demonoidt","files":1,"time":1449323052,"description":"Samples\r\n \nhttp://adultwallpapers.co.in/pervert-desi-indian-housewife/\r\n \nhttp://adultwallpapers.co.in/pervert-desi-indian-housewife-2/\r\n \nhttp://adultwallpapers.co.in/pervert-desi-indian-housewife-3/\r\n \nhttp://demonoid.co/2015/12/05/pervert-desi-indian-housewife/","torrent":{"xt":"urn:btih:fc6c80867debcda85a88e7707b7ce729fd976456","amp;dn":"Pervert+Desi+Indian+Housewife","amp;tr":["udp%3A%2F%2Ftracker.leechers-paradise.org%3A6969","udp%3A%2F%2Fzer0day.ch%3A1337","udp%3A%2F%2Fopen.demonii.com%3A1337","udp%3A%2F%2Ftracker.coppersurfer.tk%3A6969","udp%3A%2F%2Fexodus.desync.com%3A6969"],"infoHash":"fc6c80867debcda85a88e7707b7ce729fd976456","infoHashBuffer":{"type":"Buffer","data":[252,108,128,134,125,235,205,168,90,136,231,112,123,124,231,41,253,151,100,86]},"announce":[],"urlList":[]}}