{"title":"The Training of O--ToO-29659 Audrey Hollander and Wolf Hollander","uid":8600717,"size":2921974359,"categoryP":"porn","categoryS":"hd___movies","magnet":"?xt=urn:btih:fec0c143a5c7082b65c25d8ad7161adbf2fe4532&amp;dn=The+Training+of+O--ToO-29659+Audrey+Hollander+and+Wolf+Hollander&amp;tr=udp%3A%2F%2Ftracker.openbittorrent.com%3A80&amp;tr=udp%3A%2F%2Fopen.demonii.com%3A1337&amp;tr=udp%3A%2F%2Ftracker.coppersurfer.tk%3A6969&amp;tr=udp%3A%2F%2Fexodus.desync.com%3A6969","seeders":1,"leechers":2,"uploader":"merzedes","files":-1,"time":1371872313,"description":"Training of a Party Girl, Day Three\n\nJun 21, 2013 - Performers: Audrey Hollander  and  Wolf Hollander \n  \n\nMP4 and WMV + Pics.\n  \n\nI the Burden\nShe wants a collar. I give her a collar of steel she never wants to wear again. \n\nII the Box\nSensory deprivation and nipple training with my thumb up her ass. \n\nIII Little Cock Sucker\nI make her beg for that hard gimp dick. Before I let her show of her oral skill, I stuff her ass with a rubber cock on a stick. \n\nIV Anal Whore\nThe order is simple: show me how much of an ass whore you can really be.\n\nScreens &lt;a href=&quot;\nhttp://www.thetrainingofo.com/site/shoot.jsp?shootId=29659&quot; rel=&quot;nofollow&quot; target=&quot;_NEW&quot;&gt;\nhttp://www.thetrainingofo.com/site/shoot.jsp?shootId=29659&lt;/a&gt;\n\n11 000 uploads and counting, 12k here we come :) And as usual, if you still like what Shallow2 and I upload, how about leaving us a nice comment below ? :)  \n  \nCheers  :-)  \n\n","torrent":{"xt":"urn:btih:fec0c143a5c7082b65c25d8ad7161adbf2fe4532","amp;dn":"The+Training+of+O--ToO-29659+Audrey+Hollander+and+Wolf+Hollander","amp;tr":["udp%3A%2F%2Ftracker.openbittorrent.com%3A80","udp%3A%2F%2Fopen.demonii.com%3A1337","udp%3A%2F%2Ftracker.coppersurfer.tk%3A6969","udp%3A%2F%2Fexodus.desync.com%3A6969"],"infoHash":"fec0c143a5c7082b65c25d8ad7161adbf2fe4532","infoHashBuffer":{"type":"Buffer","data":[254,192,193,67,165,199,8,43,101,194,93,138,215,22,26,219,242,254,69,50]},"announce":[],"urlList":[]}}